typedframe/__init__.py
typedframe/base.py
typedframe/pandas_.py
typedframe/polars_.py
typedframe-0.11.0.dist-info/LICENSE
typedframe-0.11.0.dist-info/METADATA
typedframe-0.11.0.dist-info/WHEEL
typedframe-0.11.0.dist-info/top_level.txt
typedframe-0.11.0.dist-info/RECORD
