Metadata-Version: 2.1
Name: typedframe
Version: 0.11.0
Summary: Typed Wrappers over Pandas and Polars DataFrames with schema validation
Home-page: https://github.com/areshytko/typedframe
Author: Alexander Reshytko
Author-email: alexander@reshytko.com
License: MIT
Classifier: License :: OSI Approved :: MIT License
Classifier: Programming Language :: Python :: 3
Classifier: Programming Language :: Python :: 3.8
License-File: LICENSE
Provides-Extra: pandas
Requires-Dist: pandas ; extra == 'pandas'
Requires-Dist: numpy ; extra == 'pandas'
Provides-Extra: polars
Requires-Dist: polars ; extra == 'polars'
Requires-Dist: pyarrow ; extra == 'polars'
